graphsp.py
graphsp-1.0.0.dist-info/LICENSE
graphsp-1.0.0.dist-info/METADATA
graphsp-1.0.0.dist-info/WHEEL
graphsp-1.0.0.dist-info/top_level.txt
graphsp-1.0.0.dist-info/RECORD
