Metadata-Version: 2.1
Name: graphsp
Version: 1.0.0
Summary: Graphsp Package for Graph Data Structure
Home-page: https://github.com/jainam2385/graphsp
Author: Jainam Shah
License: UNKNOWN
Keywords: graph,algorithms,DFS,BFS,Dijkstra,Floyd Warshall
Platform: UNKNOWN
Classifier: Programming Language :: Python :: 3
Classifier: License :: OSI Approved :: MIT License
Classifier: Operating System :: OS Independent
Requires-Python: >=3.6
